{"cameraMode":{"drawMode":0,"name":"Shaded","section":"Shading Mode"},"sceneLighting":true,"audioPlay":false,"sceneViewState":{"m_AlwaysRefresh":false,"showFog":true,"showSkybox":true,"showFlares":true,"showImageEffects":true,"showParticleSystems":true,"showVisualEffectGraphs":true,"m_FxEnabled":true},"in2DMode":false,"pivot":{"x":360.0,"y":363.5,"z":0.0},"rotation":{"x":-0.0721595361828804,"y":-0.04875583201646805,"z":0.0035318166483193638,"w":-0.9961980581283569},"size":511.5977478027344,"orthographic":false}